superu/__init__.py
superu/core.py
superu/example.py
superu-2025.11.7.1.dist-info/METADATA
superu-2025.11.7.1.dist-info/WHEEL
superu-2025.11.7.1.dist-info/top_level.txt
superu-2025.11.7.1.dist-info/RECORD
