Metadata-Version: 2.4
Name: superu
Version: 2025.11.7.1
Summary: SuperU SDK to make AI calls - Create intelligent voice assistants for automated phone calls
Author-email: Paras Chhugani <paras@superu.ai>
Maintainer-email: Paras Chhugani <peoband@gmail.com>
License: MIT
Project-URL: Homepage, https://dev.superu.ai
Project-URL: Documentation, https://dev.superu.ai
Project-URL: Repository, https://github.com/superu/superu-python
Project-URL: Issues, https://github.com/superu/superu-python/issues
Project-URL: Changelog, https://github.com/superu/superu-python/releases
Keywords: ai,voice,assistant,phone,calls,automation,superu,sdk
Classifier: Development Status :: 4 - Beta
Classifier: Intended Audience :: Developers
Classifier: License :: OSI Approved :: MIT License
Classifier: Programming Language :: Python :: 3
Classifier: Programming Language :: Python :: 3.7
Classifier: Programming Language :: Python :: 3.8
Classifier: Programming Language :: Python :: 3.9
Classifier: Programming Language :: Python :: 3.10
Classifier: Programming Language :: Python :: 3.11
Classifier: Programming Language :: Python :: 3.12
Classifier: Topic :: Communications :: Telephony
Classifier: Topic :: Software Development :: Libraries :: Python Modules
Classifier: Topic :: Internet :: WWW/HTTP :: Dynamic Content
Classifier: Operating System :: OS Independent
Requires-Python: >=3.7
Requires-Dist: plivo
Requires-Dist: requests
